{
    "steps": [
        {
            "sequence": 1,
            "describe": "tap avatar to logout",
            "element": "vlauncher_avatar",
            "gesture": "tap_by_id",
            "args": "",
            "x": "",
            "y": ""
        },
        {
            "sequence": 2,
            "describe": "tap 'sign out' button",
            "element": "vlauncher_avatar_sign",
            "gesture": "tap_by_id",
            "args": "",
            "x": "",
            "y": ""
        },
        {
            "sequence": 3,
            "describe": "tap 'sign out' button on the popup",
            "element": "vlauncher_avatar_btn_logout",
            "gesture": "tap_by_id",
            "args": "",
            "x": "",
            "y": ""
        },
        {
            "sequence": "wait",
            "describe": "wait for logout finish",
            "element": "",
            "gesture": "time_wait",
            "args": "3",
            "x": "",
            "y": ""
        },
        {
            "sequence": 4,
            "describe": "tap 'guest' button back to homepage",
            "element": "vlauncher_btn_guest",
            "gesture": "tap_by_id",
            "args": "",
            "x": "",
            "y": ""
        },
        {
            "sequence": 5,
            "describe": "crop avatar image to compare",
            "element": "vlauncher_avatar",
            "gesture": "crop_byID",
            "args": [
                "compareshot_1"
            ],
            "x": "",
            "y": ""
        },
        {
            "sequence": 6,
            "describe": "open settings activity",
            "element": [
                "settings_package",
                "settings_time_activity"
            ],
            "gesture": "open_activity",
            "args": "",
            "x": "",
            "y": ""
        },
        {
            "sequence": 7,
            "describe": "open time zone list",
            "element": "settings_btn_time_zone",
            "gesture": "tap_by_id",
            "args": "",
            "x": "",
            "y": ""
        },
        {
            "sequence": 8,
            "describe": "open time zone list",
            "element": "settings_window_time_zone",
            "gesture": "scroll_down_element",
            "args": "",
            "x": "",
            "y": ""
        },
        {
            "sequence": 9,
            "describe": "select taipei time zone to change to +8 taipei time",
            "element": "//*[@text='GMT+8:00 Taipei']",
            "gesture": "tap_by_xpath",
            "args": "",
            "x": "",
            "y": ""
        },
        {
            "sequence": 10,
            "describe": "back to homepage",
            "element": "",
            "gesture": "homepage",
            "args": "",
            "x": "",
            "y": ""
        },
        {
            "sequence": 11,
            "describe": "tap avatar to logout",
            "element": "vlauncher_avatar",
            "gesture": "tap_by_id",
            "args": "",
            "x": "",
            "y": ""
        },
        {
            "sequence": 12,
            "describe": "tap 'sign out' button",
            "element": "vlauncher_avatar_sign",
            "gesture": "tap_by_id",
            "args": "",
            "x": "",
            "y": ""
        },
        {
            "sequence": 13,
            "describe": "tap 'sign out' button on the popup",
            "element": "vlauncher_avatar_btn_logout",
            "gesture": "tap_by_id",
            "args": "",
            "x": "",
            "y": ""
        },
        {
            "sequence": 14,
            "describe": "tap 'sign in' button to the login page",
            "element": "vlauncher_btn_sign_in",
            "gesture": "tap_by_id",
            "args": "",
            "x": "",
            "y": ""
        },
        {
            "sequence": 15,
            "describe": "tap 'education SSO' button to the login page",
            "element": "authenticator_btn_edu",
            "gesture": "tap_by_id",
            "args": "",
            "x": "",
            "y": ""
        },
        {
            "sequence": 16,
            "describe": "input account",
            "element": "authenticator_edu_account",
            "gesture": "sendKey_byID",
            "args": [0,"zealcloud"],
            "x": "",
            "y": ""
        },
        {
            "sequence": 17,
            "describe": "input password and verification code to login",
            "element": "authenticator_edu_password",
            "gesture": "identify_edu_verification_code",
            "args": "Viewtest123@@",
            "x": "",
            "y": ""
        },
        {
            "sequence": 18,
            "describe": "crop avatar image to compare",
            "element": "vlauncher_avatar",
            "gesture": "crop_byID",
            "args": [
                "compareshot_2"
            ],
            "x": "",
            "y": ""
        },
        {
            "sequence": 19,
            "describe": "compare two screenshots different to verify login",
            "element": [
                "compareshot_1.png",
                "compareshot_2.png"
            ],
            "gesture": "compare_images_pixel",
            "args": "",
            "x": "",
            "y": ""
        }
    ]
}